neo_taker/__init__.py
neo_taker/data_classes.py
neo_taker/hooks.py
neo_taker/model.py
neo_taker/model_maps.py
neo_taker/component_maps/__init__.py
neo_taker/component_maps/map_data_classes.py
neo_taker/component_maps/map_utils.py
neo_taker/component_maps/maps.py
neo_taker/component_maps/modelling_gemma3.py
neo_taker/component_maps/modelling_gemma3_textonly.py
neo_taker/component_maps/modelling_gpt2.py
neo_taker/component_maps/modelling_llama.py
neo_taker/component_maps/modelling_mistral.py
taker/__init__.py
taker/activations.py
taker/data_classes.py
taker/detoxify.py
taker/eval.py
taker/hooks.py
taker/mia.py
taker/model.py
taker/model_maps.py
taker/model_repos.py
taker/nn.py
taker/parser.py
taker/prune.py
taker/scoring.py
taker/texts.py
taker/vit_processor.py
transformer_lens/ActivationCache.py
transformer_lens/BertNextSentencePrediction.py
transformer_lens/FactoredMatrix.py
transformer_lens/HookedEncoder.py
transformer_lens/HookedEncoderDecoder.py
transformer_lens/HookedTransformer.py
transformer_lens/HookedTransformerConfig.py
transformer_lens/SVDInterpreter.py
transformer_lens/__init__.py
transformer_lens/evals.py
transformer_lens/head_detector.py
transformer_lens/hook_points.py
transformer_lens/loading_from_pretrained.py
transformer_lens/past_key_value_caching.py
transformer_lens/patching.py
transformer_lens/train.py
transformer_lens/utils.py
transformer_lens/components/__init__.py
transformer_lens/components/abstract_attention.py
transformer_lens/components/attention.py
transformer_lens/components/bert_block.py
transformer_lens/components/bert_embed.py
transformer_lens/components/bert_mlm_head.py
transformer_lens/components/bert_nsp_head.py
transformer_lens/components/bert_pooler.py
transformer_lens/components/embed.py
transformer_lens/components/grouped_query_attention.py
transformer_lens/components/layer_norm.py
transformer_lens/components/layer_norm_pre.py
transformer_lens/components/pos_embed.py
transformer_lens/components/rms_norm.py
neo_taker-0.1.2.dist-info/METADATA
neo_taker-0.1.2.dist-info/WHEEL
neo_taker-0.1.2.dist-info/top_level.txt
neo_taker-0.1.2.dist-info/RECORD
