Metadata-Version: 2.4
Name: neo-taker
Version: 0.1.2
Summary: New version of Taker (Transformer Activation taKER)
Project-URL: Homepage, https://github.com/nickypro/neo-taker
Project-URL: Repository, https://github.com/nickypro/neo-taker
Requires-Python: >=3.10
Requires-Dist: transformer-lens>=2.16.1
Requires-Dist: transformers>=4.55.2
Requires-Dist: welford-torch>=0.2.5
